ansutr/__init__.py
ansutr/transliteration/__init__.py
ansutr/transliteration/__metadata.py
ansutr/transliteration/utils.py
ansutr/transliteration/xlit_server.py
ansutr/transliteration/xlit_src.py
ansutr/transliteration/rnn/__init__.py
ansutr/transliteration/rnn/core.py
ansutr/transliteration/rnn/engine.py
ansutr/transliteration/rnn/network.py
ansutr/transliteration/transformer/__init__.py
ansutr/transliteration/transformer/base_engine.py
ansutr/transliteration/transformer/custom_interactive.py
ansutr/transliteration/transformer/en2indic.py
ansutr/transliteration/transformer/indic2en.py
ansutr_transliteration-1.1.3.dist-info/METADATA
ansutr_transliteration-1.1.3.dist-info/WHEEL
ansutr_transliteration-1.1.3.dist-info/top_level.txt
ansutr_transliteration-1.1.3.dist-info/RECORD
