Metadata-Version: 2.1
Name: ansutr-transliteration
Version: 1.1.3
Summary: Indic-Xlit: Transliteration library for Indic Languages. Conversion of text from English to 21 languages of South Asia.
Home-page: https://github.com/ansunlp/transliterator
Author: Sanjana
Author-email: ansunlp123@gmail.com
License: MIT
Project-URL: Our Research, https://ai4bharat.org/transliteration
Project-URL: Demo Website, https://xlit.ai4bharat.org
Project-URL: Report Issues, https://github.com/AI4Bharat/IndicXlit/issues
Project-URL: Source Code, https://github.com/AI4Bharat/IndicXlit/tree/master/app
Platform: UNKNOWN
Classifier: Programming Language :: Python :: 3
Classifier: License :: OSI Approved :: MIT License
Classifier: Operating System :: OS Independent
Classifier: Topic :: Scientific/Engineering :: Artificial Intelligence
Classifier: Topic :: Software Development :: Libraries
Requires-Python: >=3.6
Requires-Dist: pydload
Requires-Dist: flask
Requires-Dist: flask-cors
Requires-Dist: Flask-Limiter
Requires-Dist: gevent
Requires-Dist: sacremoses
Requires-Dist: pandas
Requires-Dist: tqdm
Requires-Dist: ujson
Requires-Dist: mock
Requires-Dist: tensorboardX
Requires-Dist: pyarrow
Requires-Dist: fairseq
Requires-Dist: urduhack
Requires-Dist: indic-nlp-library
